flacmirror/__init__.py
flacmirror/__main__.py
flacmirror/encode.py
flacmirror/files.py
flacmirror/main.py
flacmirror/misc.py
flacmirror/options.py
flacmirror/processes.py
flacmirror/queue.py
flacmirror-0.3.1.dist-info/METADATA
flacmirror-0.3.1.dist-info/WHEEL
flacmirror-0.3.1.dist-info/entry_points.txt
flacmirror-0.3.1.dist-info/licenses/LICENSE
flacmirror-0.3.1.dist-info/RECORD
