Metadata-Version: 2.1
Name: flacmirror
Version: 0.3.1
Summary: Tool for syncing flac files while additionally converting them
Project-URL: Documentation, https://github.com/mschulteg/flacmirror#readme
Project-URL: Issues, https://github.com/mschulteg/flacmirror/issues
Project-URL: Source, https://github.com/mschulteg/flacmirror
Author-email: Moritz Schulte <mschulte.g@gmail.com>
License-Expression: MIT
License-File: LICENSE
Classifier: Programming Language :: Python
Classifier: Programming Language :: Python :: 3.7
Classifier: Programming Language :: Python :: 3.8
Classifier: Programming Language :: Python :: 3.9
Classifier: Programming Language :: Python :: 3.10
Classifier: Programming Language :: Python :: Implementation :: CPython
Classifier: Programming Language :: Python :: Implementation :: PyPy
Requires-Python: >=3.7
